pypi_project-0.0.1.11.data/scripts/pypr
pypi_project-0.0.1.11.data/scripts/pypr.bat
pypi_project-0.0.1.11.data/scripts/pypr.completion.sh
pypiproject/__init__.py
pypiproject/__main__.py
pypiproject/version.py
pypiproject/core/__init__.py
pypiproject/core/pypiproject_core.py
pypiproject/core/pypiproject_core_unittest.py
pypi_project-0.0.1.11.dist-info/METADATA
pypi_project-0.0.1.11.dist-info/WHEEL
pypi_project-0.0.1.11.dist-info/top_level.txt
pypi_project-0.0.1.11.dist-info/zip-safe
pypi_project-0.0.1.11.dist-info/RECORD
