Metadata-Version: 2.1
Name: pypi-project
Version: 0.0.1.11
Summary: pypi-project - Empty example PYPI package by The1bit
Home-page: https://github.com/the1bit/pypi-project
Author: the1bit
Author-email: youremail@mustbe.valid
License: MIT
Keywords: python the1bithu
Platform: UNKNOWN
Classifier: Development Status :: 3 - Alpha
Classifier: Operating System :: Microsoft :: Windows
Classifier: Operating System :: POSIX :: Linux
Classifier: Intended Audience :: Developers
Classifier: Topic :: Software Development :: Build Tools
Classifier: License :: OSI Approved :: MIT License
Classifier: Programming Language :: Python
Classifier: Programming Language :: Python :: 2
Classifier: Programming Language :: Python :: 2.7
Requires-Python: >=2.6, <3
Requires-Dist: docopt
